{
  "project_info": {
    "project_number": "912796320695",
    "project_id": "espcar-85500",
    "storage_bucket": "espcar-85500.firebasestorage.app"
  },
  "client": [
    {
      "client_info": {
        "mobilesdk_app_id": "1:912796320695:android:9f767aa64226167c239e32",
        "android_client_info": {
          "package_name": "com.example.espcontroller2"
        }
      },
      "oauth_client": [],
      "api_key": [
        {
          "current_key": "AIzaSyA-o4nInMJClJjJhihGMiMjGOfTaLDS2bw"
        }
      ],
      "services": {
        "appinvite_service": {
          "other_platform_oauth_client": []
        }
      }
    }
  ],
  "configuration_version": "1"
}